{
  "db_name": "PostgreSQL",
  "query": "SELECT id, owner_user_id, parent_id, name, node_type, status, deleted_at, created_at, updated_at\n        FROM nodes \n        WHERE id = $1",
  "describe": {
    "columns": [
      {
        "ordinal": 0,
        "name": "id",
        "type_info": "Uuid"
      },
      {
        "ordinal": 1,
        "name": "owner_user_id",
        "type_info": "Uuid"
      },
      {
        "ordinal": 2,
        "name": "parent_id",
        "type_info": "Uuid"
      },
      {
        "ordinal": 3,
        "name": "name",
        "type_info": "Text"
      },
      {
        "ordinal": 4,
        "name": "node_type",
        "type_info": "Text"
      },
      {
        "ordinal": 5,
        "name": "status",
        "type_info": "Text"
      },
      {
        "ordinal": 6,
        "name": "deleted_at",
        "type_info": "Timestamptz"
      },
      {
        "ordinal": 7,
        "name": "created_at",
        "type_info": "Timestamptz"
      },
      {
        "ordinal": 8,
        "name": "updated_at",
        "type_info": "Timestamptz"
      }
    ],
    "parameters": {
      "Left": [
        "Uuid"
      ]
    },
    "nullable": [
      false,
      false,
      true,
      false,
      false,
      false,
      true,
      false,
      false
    ]
  },
  "hash": "c421686d2dd0dd0bafafd2fc5ec45208d583e7352a565506f69e9c8f5a4797db"
}
